fastdf/__init__.py
fastdf/core.py
fastdf-0.1.3.dist-info/METADATA
fastdf-0.1.3.dist-info/WHEEL
fastdf-0.1.3.dist-info/top_level.txt
fastdf-0.1.3.dist-info/RECORD
